astroView/__init__.py
astroView/viewer.py
astroview-0.1.3.dist-info/licenses/LICENSE.txt
astroview-0.1.3.dist-info/METADATA
astroview-0.1.3.dist-info/WHEEL
astroview-0.1.3.dist-info/top_level.txt
astroview-0.1.3.dist-info/RECORD
