Metadata-Version: 2.4
Name: AstroView
Version: 0.1.3
Summary: A tool for visualizing asteroid orbits and sky positions using Skyfield, Astroquery, Plotly, and Matplotlib.
Author-email: Thara Caba <tharacaba@gmail.com>, Nikoo Hosseininezhad <nikoohn1996@gmail.com>, Qifeng Cheng <fionachengqf@gmail.com>
License-Expression: MIT
Requires-Python: >=3.8
License-File: LICENSE.txt
Requires-Dist: skyfield>=1.45
Requires-Dist: astroquery>=0.4.7
Requires-Dist: astropy>=5.0
Requires-Dist: numpy>=1.22
Requires-Dist: plotly>=5.0
Requires-Dist: matplotlib>=3.5
Dynamic: license-file
